mindchain/__init__.py
mindchain/cli.py
mindchain/core/__init__.py
mindchain/core/agent.py
mindchain/core/errors.py
mindchain/core/orchestrator.py
mindchain/mcp/__init__.py
mindchain/mcp/mcp.py
mindchain/mcp/metrics.py
mindchain/mcp/policies.py
mindchain/mcp/resource_manager.py
mindchain/memory/__init__.py
mindchain/memory/memory_manager.py
mindchain/py.typed
mindchain/version.py
mindchain-0.1.7.dist-info/LICENSE
mindchain-0.1.7.dist-info/METADATA
mindchain-0.1.7.dist-info/WHEEL
mindchain-0.1.7.dist-info/entry_points.txt
mindchain-0.1.7.dist-info/RECORD
