Metadata-Version: 2.1
Name: mindchain
Version: 0.1.7
Summary: An agentic AI framework with Master Control Program (MCP) supervision
Home-page: https://github.com/Ali-Beg/mindchain
License: MIT
Author: Ali Beg
Author-email: mbeg937@gmail.com
Requires-Python: >=3.9,<3.11
Classifier: Development Status :: 3 - Alpha
Classifier: Intended Audience :: Developers
Classifier: License :: OSI Approved :: MIT License
Classifier: Programming Language :: Python :: 3
Classifier: Programming Language :: Python :: 3.9
Classifier: Programming Language :: Python :: 3.10
Classifier: Programming Language :: Python :: 3.8
Requires-Dist: fastapi (>=0.100.0)
Requires-Dist: langchain (>=0.0.267)
Requires-Dist: numpy (>=1.23.0)
Requires-Dist: openai (>=0.27.0)
Requires-Dist: pydantic (>=2.0.0)
Requires-Dist: python-dotenv (>=0.21.0)
Requires-Dist: requests (>=2.28.0)
Requires-Dist: uvicorn (>=0.22.0)
Project-URL: Documentation, https://ali-beg.github.io/mindchain
Project-URL: Repository, https://github.com/Ali-Beg/mindchain
